dht11_spi/__init__.py
dht11_spi/__main__.py
dht11_spi-1.0.5.dist-info/LICENSE
dht11_spi-1.0.5.dist-info/METADATA
dht11_spi-1.0.5.dist-info/WHEEL
dht11_spi-1.0.5.dist-info/top_level.txt
dht11_spi-1.0.5.dist-info/RECORD
