Metadata-Version: 2.1
Name: dht11-spi
Version: 1.0.5
Summary: Python module to use the SPI bus to read DHT11/DHT22 sensors.
Author-email: Thomas Dunteman <git@learningtopi.com>
Project-URL: Homepage, https://www.learningtopi.com/python-modules-applications/dht11_spi/
Project-URL: Bug Tracker, https://github.com/LearningToPi/dht11_spi/issues
Project-URL: Source Code, https://github.com/LearningToPi/dht11_spi
Keywords: dht11,dht22,spi
Classifier: Topic :: System :: Logging
Classifier: License :: OSI Approved :: MIT License
Classifier: Programming Language :: Python :: 3
Classifier: Topic :: Software Development :: Libraries :: Python Modules
Classifier: Topic :: System :: Hardware :: Hardware Drivers
Requires-Python: >=3.6
License-File: LICENSE
Requires-Dist: wheel
Requires-Dist: logging-handler
Requires-Dist: spidev
Requires-Dist: gpiod
